nr/__init__.py
nr/caching/__init__.py
nr/caching/api.py
nr/caching/py.typed
nr/caching/adapters/__init__.py
nr/caching/adapters/json.py
nr/caching/adapters/mapping.py
nr/caching/stores/__init__.py
nr/caching/stores/jsondirectory.py
nr/caching/stores/sqlite.py
nr.caching-0.4.1.dist-info/LICENSE.txt
nr.caching-0.4.1.dist-info/METADATA
nr.caching-0.4.1.dist-info/WHEEL
nr.caching-0.4.1.dist-info/top_level.txt
nr.caching-0.4.1.dist-info/RECORD
