Metadata-Version: 2.1
Name: nr.caching
Version: 0.4.1
Summary: A simple key-value caching API with default implementations for an SQLite3 storage backend and a JSON convenience layer.
Home-page: https://github.com/NiklasRosenstein/nr-python
Author: Niklas Rosenstein
Author-email: rosensteinniklas@gmail.com
License: MIT
Platform: UNKNOWN
Requires-Python: >=3.6.0,<4.0.0
Requires-Dist: nr.pylang.utils (<1.0.0,>=0.1.3)
Requires-Dist: overrides (<4.0.0,>=3.1.0)
